sphinxcontrib_googlechart-0.2.1-py2.7-nspkg.pth
sphinxcontrib/googlechart/__init__.py
sphinxcontrib/googlechart/core.py
sphinxcontrib/googlechart/graphviz.py
sphinxcontrib/googlechart/parser.py
sphinxcontrib/googlechart/regions.py
sphinxcontrib_googlechart-0.2.1.dist-info/DESCRIPTION.rst
sphinxcontrib_googlechart-0.2.1.dist-info/METADATA
sphinxcontrib_googlechart-0.2.1.dist-info/metadata.json
sphinxcontrib_googlechart-0.2.1.dist-info/namespace_packages.txt
sphinxcontrib_googlechart-0.2.1.dist-info/RECORD
sphinxcontrib_googlechart-0.2.1.dist-info/top_level.txt
sphinxcontrib_googlechart-0.2.1.dist-info/WHEEL
